{
  "updatedAt": "2026-07-02T01:27:22.405Z",
  "source": "10bet-playtech-dom",
  "partial": false,
  "events": [
    {
      "eventId": "10bet_29420903",
      "title": "Cuiaba MT - America Mineiro MG",
      "homeTeam": "Cuiaba MT",
      "awayTeam": "America Mineiro MG",
      "startTime": "2026-07-02T23:00:00.000Z",
      "league": "Brazil - Serie B",
      "sport": "football",
      "odds": {
        "home": 1.84,
        "draw": 3.2,
        "away": 4.7
      },
      "totals": [
        {
          "line": 2.5,
          "over": 2.45,
          "under": 1.533
        }
      ]
    },
    {
      "eventId": "10bet_29422554",
      "title": "Fortaleza CE - Ponte Preta SP",
      "homeTeam": "Fortaleza CE",
      "awayTeam": "Ponte Preta SP",
      "startTime": "2026-07-03T00:00:00.000Z",
      "league": "Brazil - Serie B",
      "sport": "football",
      "odds": {
        "home": 1.3,
        "draw": 4.75,
        "away": 11
      },
      "totals": [
        {
          "line": 2.5,
          "over": 1.75,
          "under": 2.05
        }
      ]
    },
    {
      "eventId": "10bet_29420279",
      "title": "Riga FC - FK Jelgava",
      "homeTeam": "Riga FC",
      "awayTeam": "FK Jelgava",
      "startTime": "2026-07-03T16:00:00.000Z",
      "league": "Latvia - Virsliga",
      "sport": "football",
      "odds": {
        "home": 1.222,
        "draw": 5.4,
        "away": 10.8
      },
      "totals": [
        {
          "line": 3.5,
          "over": 1.95,
          "under": 1.769
        }
      ]
    },
    {
      "eventId": "10bet_29422570",
      "title": "Birmingham Legion FC - Detroit City",
      "homeTeam": "Birmingham Legion FC",
      "awayTeam": "Detroit City",
      "startTime": "2026-07-03T00:00:00.000Z",
      "league": "USA - USL Championship",
      "sport": "football",
      "odds": {
        "home": 2.65,
        "draw": 3.3,
        "away": 2.375
      },
      "totals": [
        {
          "line": 2.5,
          "over": 1.85,
          "under": 1.85
        }
      ]
    },
    {
      "eventId": "10bet_29444634",
      "title": "Loudoun United FC - Sporting Jax",
      "homeTeam": "Loudoun United FC",
      "awayTeam": "Sporting Jax",
      "startTime": "2026-07-03T23:00:00.000Z",
      "league": "USA - USL Championship",
      "sport": "football",
      "odds": {
        "home": 1.571,
        "draw": 3.95,
        "away": 4.8
      },
      "totals": [
        {
          "line": 2.5,
          "over": 1.55,
          "under": 2.35
        }
      ]
    },
    {
      "eventId": "10bet_29443175",
      "title": "Derry City - Waterford United",
      "homeTeam": "Derry City",
      "awayTeam": "Waterford United",
      "startTime": "2026-07-03T18:45:00.000Z",
      "league": "Premier Division",
      "sport": "football",
      "odds": {
        "home": 1.43,
        "draw": 4.33,
        "away": 7.1
      },
      "totals": [
        {
          "line": 2.5,
          "over": 1.666,
          "under": 2.15
        }
      ]
    },
    {
      "eventId": "10bet_29442351",
      "title": "Drogheda United - Bohemians Dublin",
      "homeTeam": "Drogheda United",
      "awayTeam": "Bohemians Dublin",
      "startTime": "2026-07-03T18:45:00.000Z",
      "league": "Premier Division",
      "sport": "football",
      "odds": {
        "home": 4.55,
        "draw": 3.7,
        "away": 1.72
      },
      "totals": [
        {
          "line": 2.5,
          "over": 1.8,
          "under": 2
        }
      ]
    },
    {
      "eventId": "10bet_29442357",
      "title": "Saint Patrick FC - Galway United FC",
      "homeTeam": "Saint Patrick FC",
      "awayTeam": "Galway United FC",
      "startTime": "2026-07-03T18:45:00.000Z",
      "league": "Premier Division",
      "sport": "football",
      "odds": {
        "home": 1.4,
        "draw": 4.55,
        "away": 7.3
      },
      "totals": [
        {
          "line": 2.5,
          "over": 1.615,
          "under": 2.25
        }
      ]
    },
    {
      "eventId": "10bet_29442354",
      "title": "Shelbourne Dublin - FC Dundalk",
      "homeTeam": "Shelbourne Dublin",
      "awayTeam": "FC Dundalk",
      "startTime": "2026-07-03T18:45:00.000Z",
      "league": "Premier Division",
      "sport": "football",
      "odds": {
        "home": 2.16,
        "draw": 3.7,
        "away": 2.98
      },
      "totals": [
        {
          "line": 2.5,
          "over": 1.65,
          "under": 2.2
        }
      ]
    },
    {
      "eventId": "10bet_29442359",
      "title": "Sligo Rovers - Shamrock Rovers",
      "homeTeam": "Sligo Rovers",
      "awayTeam": "Shamrock Rovers",
      "startTime": "2026-07-03T18:45:00.000Z",
      "league": "Premier Division",
      "sport": "football",
      "odds": {
        "home": 5.9,
        "draw": 3.95,
        "away": 1.55
      },
      "totals": [
        {
          "line": 2.5,
          "over": 1.833,
          "under": 1.95
        }
      ]
    },
    {
      "eventId": "10bet_29170824",
      "title": "IK Sirius - Mjällby AIF",
      "homeTeam": "IK Sirius",
      "awayTeam": "Mjällby AIF",
      "startTime": "2026-07-03T17:00:00.000Z",
      "league": "Sweden - Allsvenskan",
      "sport": "football",
      "odds": {
        "home": 1.7,
        "draw": 3.9,
        "away": 4.4
      },
      "totals": [
        {
          "line": 2.5,
          "over": 1.666,
          "under": 2.2
        }
      ]
    },
    {
      "eventId": "10bet_29420278",
      "title": "Yunnan Yukun - Henan Songshan Longmen",
      "homeTeam": "Yunnan Yukun",
      "awayTeam": "Henan Songshan Longmen",
      "startTime": "2026-07-03T12:00:00.000Z",
      "league": "China - Super League",
      "sport": "football",
      "odds": {
        "home": 2.4,
        "draw": 3.55,
        "away": 2.55
      },
      "totals": [
        {
          "line": 3.5,
          "over": 2.2,
          "under": 1.615
        }
      ]
    },
    {
      "eventId": "10bet_29415790",
      "title": "Thor Akureyri - KR Reykjavik",
      "homeTeam": "Thor Akureyri",
      "awayTeam": "KR Reykjavik",
      "startTime": "2026-07-02T20:30:00.000Z",
      "league": "Iceland - Premier League",
      "sport": "football",
      "odds": {
        "home": 6.75,
        "draw": 5.8,
        "away": 1.285
      },
      "totals": [
        {
          "line": 4.5,
          "over": 1.93,
          "under": 1.8
        }
      ]
    },
    {
      "eventId": "10bet_29418336",
      "title": "Vikingur Reykjavik - Ka Akureyri",
      "homeTeam": "Vikingur Reykjavik",
      "awayTeam": "Ka Akureyri",
      "startTime": "2026-07-02T22:45:00.000Z",
      "league": "Iceland - Premier League",
      "sport": "football",
      "odds": {
        "home": 1.142,
        "draw": 6.8,
        "away": 12
      },
      "totals": [
        {
          "line": 3.5,
          "over": 1.615,
          "under": 2.2
        }
      ]
    },
    {
      "eventId": "10bet_29443046",
      "title": "FH Hafnarfjordur - Stjarnan Gardabaer",
      "homeTeam": "FH Hafnarfjordur",
      "awayTeam": "Stjarnan Gardabaer",
      "startTime": "2026-07-03T22:45:00.000Z",
      "league": "Iceland - Premier League",
      "sport": "football",
      "odds": {
        "home": 2.3,
        "draw": 4,
        "away": 2.45
      },
      "totals": [
        {
          "line": 3.5,
          "over": 1.769,
          "under": 2
        }
      ]
    },
    {
      "eventId": "10bet_29438992",
      "title": "FC KooTeePee - JIPPO",
      "homeTeam": "FC KooTeePee",
      "awayTeam": "JIPPO",
      "startTime": "2026-07-03T19:00:00.000Z",
      "league": "Finland - Ykkosliiga",
      "sport": "football",
      "odds": {
        "home": 1.95,
        "draw": 3.2,
        "away": 3.6
      },
      "totals": [
        {
          "line": 2.5,
          "over": 2.05,
          "under": 1.7
        }
      ]
    },
    {
      "eventId": "10bet_29438985",
      "title": "JaPS - SJK Akatemia",
      "homeTeam": "JaPS",
      "awayTeam": "SJK Akatemia",
      "startTime": "2026-07-03T19:00:00.000Z",
      "league": "Finland - Ykkosliiga",
      "sport": "football",
      "odds": {
        "home": 1.85,
        "draw": 3.6,
        "away": 3.5
      },
      "totals": [
        {
          "line": 2.5,
          "over": 1.65,
          "under": 2.15
        }
      ]
    },
    {
      "eventId": "10bet_29396106",
      "title": "FK Lyn - Åsane",
      "homeTeam": "FK Lyn",
      "awayTeam": "Åsane",
      "startTime": "2026-07-02T19:30:00.000Z",
      "league": "Norway - 1st Division",
      "sport": "football",
      "odds": {
        "home": 1.727,
        "draw": 4,
        "away": 3.75
      },
      "totals": [
        {
          "line": 3.5,
          "over": 2.2,
          "under": 1.615
        }
      ]
    },
    {
      "eventId": "10bet_29420277",
      "title": "Kongsvinger - Sogndal",
      "homeTeam": "Kongsvinger",
      "awayTeam": "Sogndal",
      "startTime": "2026-07-03T19:30:00.000Z",
      "league": "Norway - 1st Division",
      "sport": "football",
      "odds": {
        "home": 1.64,
        "draw": 4.1,
        "away": 4.1
      },
      "totals": [
        {
          "line": 3.5,
          "over": 1.8,
          "under": 1.93
        }
      ]
    },
    {
      "eventId": "10bet_29420296",
      "title": "Raufoss - Strommen",
      "homeTeam": "Raufoss",
      "awayTeam": "Strommen",
      "startTime": "2026-07-03T19:30:00.000Z",
      "league": "Norway - 1st Division",
      "sport": "football",
      "odds": {
        "home": 2.375,
        "draw": 3.65,
        "away": 2.45
      },
      "totals": [
        {
          "line": 3.5,
          "over": 2.2,
          "under": 1.615
        }
      ]
    },
    {
      "eventId": "10bet_29420275",
      "title": "Ranheim - Stabaek",
      "homeTeam": "Ranheim",
      "awayTeam": "Stabaek",
      "startTime": "2026-07-03T20:30:00.000Z",
      "league": "Norway - 1st Division",
      "sport": "football",
      "odds": {
        "home": 2.65,
        "draw": 3.8,
        "away": 2.15
      },
      "totals": [
        {
          "line": 3.5,
          "over": 1.85,
          "under": 1.85
        }
      ]
    },
    {
      "eventId": "10bet_29475194",
      "title": "Spanien - Österrike",
      "homeTeam": "Spanien",
      "awayTeam": "Österrike",
      "startTime": "2026-07-02T22:30:00.000Z",
      "league": "VM 2026 – matcher",
      "sport": "football",
      "odds": {
        "home": 1.34,
        "draw": 4.75,
        "away": 8.8
      },
      "totals": [
        {
          "line": 2.5,
          "over": 1.7,
          "under": 2.1
        }
      ]
    },
    {
      "eventId": "10bet_29472730",
      "title": "Portugal - Kroatien",
      "homeTeam": "Portugal",
      "awayTeam": "Kroatien",
      "startTime": "2026-07-03T02:30:00.000Z",
      "league": "VM 2026 – matcher",
      "sport": "football",
      "odds": {
        "home": 1.74,
        "draw": 3.55,
        "away": 4.7
      },
      "totals": [
        {
          "line": 2.5,
          "over": 1.85,
          "under": 1.93
        }
      ]
    },
    {
      "eventId": "10bet_29475132",
      "title": "Schweiz - Algeriet",
      "homeTeam": "Schweiz",
      "awayTeam": "Algeriet",
      "startTime": "2026-07-03T06:30:00.000Z",
      "league": "VM 2026 – matcher",
      "sport": "football",
      "odds": {
        "home": 1.97,
        "draw": 3.35,
        "away": 3.8
      },
      "totals": [
        {
          "line": 2.5,
          "over": 2.1,
          "under": 1.7
        }
      ]
    },
    {
      "eventId": "10bet_29452838",
      "title": "Australien - Egypten",
      "homeTeam": "Australien",
      "awayTeam": "Egypten",
      "startTime": "2026-07-03T21:30:00.000Z",
      "league": "VM 2026 – matcher",
      "sport": "football",
      "odds": {
        "home": 3.25,
        "draw": 2.92,
        "away": 2.38
      },
      "totals": [
        {
          "line": 1.5,
          "over": 1.571,
          "under": 2.35
        }
      ]
    },
    {
      "eventId": "10bet_29442363",
      "title": "Bray Wanderers - Athlone Town",
      "homeTeam": "Bray Wanderers",
      "awayTeam": "Athlone Town",
      "startTime": "2026-07-03T18:45:00.000Z",
      "league": "1:a Division",
      "sport": "football",
      "odds": {
        "home": 1.69,
        "draw": 3.85,
        "away": 4.55
      }
    },
    {
      "eventId": "10bet_29442366",
      "title": "Cobh Ramblers - Cork City",
      "homeTeam": "Cobh Ramblers",
      "awayTeam": "Cork City",
      "startTime": "2026-07-03T18:45:00.000Z",
      "league": "1:a Division",
      "sport": "football",
      "odds": {
        "home": 4.5,
        "draw": 3.75,
        "away": 1.73
      }
    },
    {
      "eventId": "10bet_29442374",
      "title": "Finn Harps - Wexford FC",
      "homeTeam": "Finn Harps",
      "awayTeam": "Wexford FC",
      "startTime": "2026-07-03T18:45:00.000Z",
      "league": "1:a Division",
      "sport": "football",
      "odds": {
        "home": 4.45,
        "draw": 3.7,
        "away": 1.74
      }
    },
    {
      "eventId": "10bet_29443248",
      "title": "Treaty United - Kerry FC",
      "homeTeam": "Treaty United",
      "awayTeam": "Kerry FC",
      "startTime": "2026-07-03T18:45:00.000Z",
      "league": "1:a Division",
      "sport": "football",
      "odds": {
        "home": 2.52,
        "draw": 3.25,
        "away": 2.75
      },
      "totals": [
        {
          "line": 2.5,
          "over": 2.1,
          "under": 1.727
        }
      ]
    },
    {
      "eventId": "10bet_29501784",
      "title": "Berkane - Wydad Casablanca",
      "homeTeam": "Berkane",
      "awayTeam": "Wydad Casablanca",
      "startTime": "2026-07-02T17:00:00.000Z",
      "league": "Morocco - Botola Pro",
      "sport": "football",
      "odds": {
        "home": 1.65,
        "draw": 3.3,
        "away": 5.2
      },
      "totals": [
        {
          "line": 2.5,
          "over": 2.2,
          "under": 1.615
        }
      ]
    },
    {
      "eventId": "10bet_29501785",
      "title": "Codm Meknes - FAR Rabat",
      "homeTeam": "Codm Meknes",
      "awayTeam": "FAR Rabat",
      "startTime": "2026-07-02T17:00:00.000Z",
      "league": "Morocco - Botola Pro",
      "sport": "football",
      "odds": {
        "home": 6.25,
        "draw": 3.7,
        "away": 1.48
      },
      "totals": [
        {
          "line": 2.5,
          "over": 2.1,
          "under": 1.7
        }
      ]
    },
    {
      "eventId": "10bet_29501782",
      "title": "Kawkab Marrakech - Maghreb Fez",
      "homeTeam": "Kawkab Marrakech",
      "awayTeam": "Maghreb Fez",
      "startTime": "2026-07-02T17:00:00.000Z",
      "league": "Morocco - Botola Pro",
      "sport": "football",
      "odds": {
        "home": 4.8,
        "draw": 2.95,
        "away": 1.8
      },
      "totals": [
        {
          "line": 1.5,
          "over": 1.55,
          "under": 2.35
        }
      ]
    },
    {
      "eventId": "10bet_29501779",
      "title": "Olympique Dcheira - Olympique Safi",
      "homeTeam": "Olympique Dcheira",
      "awayTeam": "Olympique Safi",
      "startTime": "2026-07-02T17:00:00.000Z",
      "league": "Morocco - Botola Pro",
      "sport": "football",
      "odds": {
        "home": 2.05,
        "draw": 3.1,
        "away": 3.45
      },
      "totals": [
        {
          "line": 2.5,
          "over": 2.2,
          "under": 1.615
        }
      ]
    },
    {
      "eventId": "10bet_29532572",
      "title": "Raja CA - Husa Hassania Agadir",
      "homeTeam": "Raja CA",
      "awayTeam": "Husa Hassania Agadir",
      "startTime": "2026-07-02T17:00:00.000Z",
      "league": "Morocco - Botola Pro",
      "sport": "football",
      "odds": {
        "home": 1.45,
        "draw": 3.75,
        "away": 6.8
      },
      "totals": [
        {
          "line": 2.5,
          "over": 2.1,
          "under": 1.7
        }
      ]
    },
    {
      "eventId": "10bet_29501778",
      "title": "Renaissance Zemamra - FUS Rabat",
      "homeTeam": "Renaissance Zemamra",
      "awayTeam": "FUS Rabat",
      "startTime": "2026-07-02T17:00:00.000Z",
      "league": "Morocco - Botola Pro",
      "sport": "football",
      "odds": {
        "home": 1.769,
        "draw": 3.25,
        "away": 4.4
      },
      "totals": [
        {
          "line": 2.5,
          "over": 2.35,
          "under": 1.55
        }
      ]
    },
    {
      "eventId": "10bet_29501781",
      "title": "UTS Union Touarga - Ittihad Tanger",
      "homeTeam": "UTS Union Touarga",
      "awayTeam": "Ittihad Tanger",
      "startTime": "2026-07-02T17:00:00.000Z",
      "league": "Morocco - Botola Pro",
      "sport": "football",
      "odds": {
        "home": 2.05,
        "draw": 3.1,
        "away": 3.45
      },
      "totals": [
        {
          "line": 2.5,
          "over": 2.35,
          "under": 1.55
        }
      ]
    },
    {
      "eventId": "10bet_29501783",
      "title": "Yacoub El Mansour - Dhj Difaa Hassani Jdidi",
      "homeTeam": "Yacoub El Mansour",
      "awayTeam": "Dhj Difaa Hassani Jdidi",
      "startTime": "2026-07-02T17:00:00.000Z",
      "league": "Morocco - Botola Pro",
      "sport": "football",
      "odds": {
        "home": 1.95,
        "draw": 3.1,
        "away": 3.75
      },
      "totals": [
        {
          "line": 2.5,
          "over": 2.35,
          "under": 1.55
        }
      ]
    }
  ]
}