{
  "updatedAt": "2026-07-02T02:40:55.475Z",
  "source": "github-actions-dom-scrape",
  "events": {
    "tn:football::e-napoli::e-barcelona::2026-07-02T02:42:00.000Z": {
      "sbobetEventId": "tn:football::e-napoli::e-barcelona::2026-07-02T02:42:00.000Z",
      "sport": "football",
      "homeTeam": "e-Napoli (ZEUS)",
      "awayTeam": "e-Barcelona (GRIMACE)",
      "startTime": "2026-07-02T02:42:00.000Z",
      "competition": null,
      "markets": [
        {
          "oddsId": "701272841",
          "marketType": "ML_1X2",
          "scope": "full",
          "runners": [
            {
              "selection": "HOME",
              "decimalOdds": 2.2
            },
            {
              "selection": "DRAW",
              "decimalOdds": 3.64
            },
            {
              "selection": "AWAY",
              "decimalOdds": 2.392
            }
          ]
        }
      ]
    },
    "tn:football::e-sweden::e-germany::2026-07-02T02:46:00.000Z": {
      "sbobetEventId": "tn:football::e-sweden::e-germany::2026-07-02T02:46:00.000Z",
      "sport": "football",
      "homeTeam": "e-Sweden (RIVAL)",
      "awayTeam": "e-Germany (DECIMATOR)",
      "startTime": "2026-07-02T02:46:00.000Z",
      "competition": null,
      "markets": [
        {
          "oddsId": "701273979",
          "marketType": "ML_1X2",
          "scope": "full",
          "runners": [
            {
              "selection": "HOME",
              "decimalOdds": 2.584
            },
            {
              "selection": "DRAW",
              "decimalOdds": 3.64
            },
            {
              "selection": "AWAY",
              "decimalOdds": 2.104
            }
          ]
        }
      ]
    },
    "tn:football::e-croatia::e-sweden::2026-07-02T02:50:00.000Z": {
      "sbobetEventId": "tn:football::e-croatia::e-sweden::2026-07-02T02:50:00.000Z",
      "sport": "football",
      "homeTeam": "e-Croatia (TROOPER)",
      "awayTeam": "e-Sweden (STORM)",
      "startTime": "2026-07-02T02:50:00.000Z",
      "competition": null,
      "markets": [
        {
          "oddsId": "701274840",
          "marketType": "ML_1X2",
          "scope": "full",
          "runners": [
            {
              "selection": "HOME",
              "decimalOdds": 2.584
            },
            {
              "selection": "DRAW",
              "decimalOdds": 3.4
            },
            {
              "selection": "AWAY",
              "decimalOdds": 2.104
            }
          ]
        }
      ]
    },
    "tn:football::e-netherlands::e-usa::2026-07-02T02:53:00.000Z": {
      "sbobetEventId": "tn:football::e-netherlands::e-usa::2026-07-02T02:53:00.000Z",
      "sport": "football",
      "homeTeam": "e-Netherlands (TEMPEST)",
      "awayTeam": "e-USA (JAEGER)",
      "startTime": "2026-07-02T02:53:00.000Z",
      "competition": null,
      "markets": [
        {
          "oddsId": "701275766",
          "marketType": "ML_1X2",
          "scope": "full",
          "runners": [
            {
              "selection": "HOME",
              "decimalOdds": 2.2
            },
            {
              "selection": "DRAW",
              "decimalOdds": 3.4
            },
            {
              "selection": "AWAY",
              "decimalOdds": 2.488
            }
          ]
        }
      ]
    },
    "tn:football::e-paris sg::e- bayern munchen::2026-07-02T02:57:00.000Z": {
      "sbobetEventId": "tn:football::e-paris sg::e- bayern munchen::2026-07-02T02:57:00.000Z",
      "sport": "football",
      "homeTeam": "e-Paris SG (ZEUS)",
      "awayTeam": "e-FC Bayern Munchen (THREAT)",
      "startTime": "2026-07-02T02:57:00.000Z",
      "competition": null,
      "markets": [
        {
          "oddsId": "701276623",
          "marketType": "ML_1X2",
          "scope": "full",
          "runners": [
            {
              "selection": "HOME",
              "decimalOdds": 2.584
            },
            {
              "selection": "DRAW",
              "decimalOdds": 3.64
            },
            {
              "selection": "AWAY",
              "decimalOdds": 2.104
            }
          ]
        }
      ]
    },
    "tn:football::e-spurs::e-newcastle utd::2026-07-02T03:01:00.000Z": {
      "sbobetEventId": "tn:football::e-spurs::e-newcastle utd::2026-07-02T03:01:00.000Z",
      "sport": "football",
      "homeTeam": "e-Spurs (RIVAL)",
      "awayTeam": "e-Newcastle UTD (ENT)",
      "startTime": "2026-07-02T03:01:00.000Z",
      "competition": null,
      "markets": [
        {
          "oddsId": "701281356",
          "marketType": "ML_1X2",
          "scope": "full",
          "runners": [
            {
              "selection": "HOME",
              "decimalOdds": 2.872
            },
            {
              "selection": "DRAW",
              "decimalOdds": 3.88
            },
            {
              "selection": "AWAY",
              "decimalOdds": 1.912
            }
          ]
        }
      ]
    },
    "tn:football::e-england::e-usa::2026-07-02T03:05:00.000Z": {
      "sbobetEventId": "tn:football::e-england::e-usa::2026-07-02T03:05:00.000Z",
      "sport": "football",
      "homeTeam": "e-England (TROOPER)",
      "awayTeam": "e-USA (ODYSSEY)",
      "startTime": "2026-07-02T03:05:00.000Z",
      "competition": null,
      "markets": [
        {
          "oddsId": "701298932",
          "marketType": "ML_1X2",
          "scope": "full",
          "runners": [
            {
              "selection": "HOME",
              "decimalOdds": 2.584
            },
            {
              "selection": "DRAW",
              "decimalOdds": 3.4
            },
            {
              "selection": "AWAY",
              "decimalOdds": 2.104
            }
          ]
        }
      ]
    },
    "tn:football::e-germany::e-england::2026-07-02T03:08:00.000Z": {
      "sbobetEventId": "tn:football::e-germany::e-england::2026-07-02T03:08:00.000Z",
      "sport": "football",
      "homeTeam": "e-Germany (INFERNO)",
      "awayTeam": "e-England (FORCE)",
      "startTime": "2026-07-02T03:08:00.000Z",
      "competition": null,
      "markets": [
        {
          "oddsId": "701307635",
          "marketType": "ML_1X2",
          "scope": "full",
          "runners": [
            {
              "selection": "HOME",
              "decimalOdds": 1.672
            },
            {
              "selection": "DRAW",
              "decimalOdds": 3.88
            },
            {
              "selection": "AWAY",
              "decimalOdds": 3.4
            }
          ]
        }
      ]
    },
    "tn:football::e-manchester city::e-real madrid::2026-07-02T03:12:00.000Z": {
      "sbobetEventId": "tn:football::e-manchester city::e-real madrid::2026-07-02T03:12:00.000Z",
      "sport": "football",
      "homeTeam": "e-Manchester City (GRIMACE)",
      "awayTeam": "e-Real Madrid (RESISTANCE)",
      "startTime": "2026-07-02T03:12:00.000Z",
      "competition": null,
      "markets": [
        {
          "oddsId": "701308993",
          "marketType": "ML_1X2",
          "scope": "full",
          "runners": [
            {
              "selection": "HOME",
              "decimalOdds": 1.912
            },
            {
              "selection": "DRAW",
              "decimalOdds": 4.072
            },
            {
              "selection": "AWAY",
              "decimalOdds": 2.584
            }
          ]
        }
      ]
    },
    "tn:football::e-aston villa::e-arsenal::2026-07-02T03:16:00.000Z": {
      "sbobetEventId": "tn:football::e-aston villa::e-arsenal::2026-07-02T03:16:00.000Z",
      "sport": "football",
      "homeTeam": "e-Aston Villa (DECIMATOR)",
      "awayTeam": "e-Arsenal (CROWN)",
      "startTime": "2026-07-02T03:16:00.000Z",
      "competition": null,
      "markets": [
        {
          "oddsId": "701310016",
          "marketType": "ML_1X2",
          "scope": "full",
          "runners": [
            {
              "selection": "HOME",
              "decimalOdds": 2.2
            },
            {
              "selection": "DRAW",
              "decimalOdds": 3.016
            },
            {
              "selection": "AWAY",
              "decimalOdds": 2.872
            }
          ]
        }
      ]
    },
    "tn:football::e-germany::e-sweden::2026-07-02T03:20:00.000Z": {
      "sbobetEventId": "tn:football::e-germany::e-sweden::2026-07-02T03:20:00.000Z",
      "sport": "football",
      "homeTeam": "e-Germany (STORM)",
      "awayTeam": "e-Sweden (MARS)",
      "startTime": "2026-07-02T03:20:00.000Z",
      "competition": null,
      "markets": [
        {
          "oddsId": "701311231",
          "marketType": "ML_1X2",
          "scope": "full",
          "runners": [
            {
              "selection": "HOME",
              "decimalOdds": 2.104
            },
            {
              "selection": "DRAW",
              "decimalOdds": 3.256
            },
            {
              "selection": "AWAY",
              "decimalOdds": 2.584
            }
          ]
        }
      ]
    },
    "tn:football::e-usa::e-germany::2026-07-02T03:23:00.000Z": {
      "sbobetEventId": "tn:football::e-usa::e-germany::2026-07-02T03:23:00.000Z",
      "sport": "football",
      "homeTeam": "e-USA (JAEGER)",
      "awayTeam": "e-Germany (INFERNO)",
      "startTime": "2026-07-02T03:23:00.000Z",
      "competition": null,
      "markets": [
        {
          "oddsId": "701312037",
          "marketType": "ML_1X2",
          "scope": "full",
          "runners": [
            {
              "selection": "HOME",
              "decimalOdds": 5.32
            },
            {
              "selection": "DRAW",
              "decimalOdds": 3.88
            },
            {
              "selection": "AWAY",
              "decimalOdds": 1.48
            }
          ]
        }
      ]
    },
    "tn:football::e- bayern munchen::e-manchester city::2026-07-02T03:27:00.000Z": {
      "sbobetEventId": "tn:football::e- bayern munchen::e-manchester city::2026-07-02T03:27:00.000Z",
      "sport": "football",
      "homeTeam": "e-FC Bayern Munchen (THREAT)",
      "awayTeam": "e-Manchester City (GRIMACE)",
      "startTime": "2026-07-02T03:27:00.000Z",
      "competition": null,
      "markets": [
        {
          "oddsId": "701313074",
          "marketType": "ML_1X2",
          "scope": "full",
          "runners": [
            {
              "selection": "HOME",
              "decimalOdds": 2.296
            },
            {
              "selection": "DRAW",
              "decimalOdds": 3.64
            },
            {
              "selection": "AWAY",
              "decimalOdds": 2.392
            }
          ]
        }
      ]
    },
    "tn:football::e-newcastle utd::e-aston villa::2026-07-02T03:31:00.000Z": {
      "sbobetEventId": "tn:football::e-newcastle utd::e-aston villa::2026-07-02T03:31:00.000Z",
      "sport": "football",
      "homeTeam": "e-Newcastle UTD (ENT)",
      "awayTeam": "e-Aston Villa (DECIMATOR)",
      "startTime": "2026-07-02T03:31:00.000Z",
      "competition": null,
      "markets": [
        {
          "oddsId": "701314004",
          "marketType": "ML_1X2",
          "scope": "full",
          "runners": [
            {
              "selection": "HOME",
              "decimalOdds": 2.104
            },
            {
              "selection": "DRAW",
              "decimalOdds": 3.64
            },
            {
              "selection": "AWAY",
              "decimalOdds": 2.584
            }
          ]
        }
      ]
    },
    "tn:football::e-usa::e-england::2026-07-02T03:35:00.000Z": {
      "sbobetEventId": "tn:football::e-usa::e-england::2026-07-02T03:35:00.000Z",
      "sport": "football",
      "homeTeam": "e-USA (ODYSSEY)",
      "awayTeam": "e-England (STORM)",
      "startTime": "2026-07-02T03:35:00.000Z",
      "competition": null,
      "markets": [
        {
          "oddsId": "701315049",
          "marketType": "ML_1X2",
          "scope": "full",
          "runners": [
            {
              "selection": "HOME",
              "decimalOdds": 2.488
            },
            {
              "selection": "DRAW",
              "decimalOdds": 3.4
            },
            {
              "selection": "AWAY",
              "decimalOdds": 2.2
            }
          ]
        }
      ]
    },
    "tn:football::e-england::e-netherlands::2026-07-02T03:38:00.000Z": {
      "sbobetEventId": "tn:football::e-england::e-netherlands::2026-07-02T03:38:00.000Z",
      "sport": "football",
      "homeTeam": "e-England (FORCE)",
      "awayTeam": "e-Netherlands (TEMPEST)",
      "startTime": "2026-07-02T03:38:00.000Z",
      "competition": null,
      "markets": [
        {
          "oddsId": "701315775",
          "marketType": "ML_1X2",
          "scope": "full",
          "runners": [
            {
              "selection": "HOME",
              "decimalOdds": 2.104
            },
            {
              "selection": "DRAW",
              "decimalOdds": 3.88
            },
            {
              "selection": "AWAY",
              "decimalOdds": 2.488
            }
          ]
        }
      ]
    },
    "tn:football::e-napoli::e-barcelona::": {
      "sbobetEventId": "tn:football::e-napoli::e-barcelona::",
      "sport": "football",
      "homeTeam": "e-Napoli (ZEUS)",
      "awayTeam": "e-Barcelona (GRIMACE)",
      "startTime": null,
      "competition": null,
      "markets": [
        {
          "oddsId": "701272845",
          "marketType": "AH",
          "scope": "full",
          "line": -0.5,
          "runners": [
            {
              "selection": "HOME",
              "decimalOdds": 2.2
            },
            {
              "selection": "AWAY",
              "decimalOdds": 1.53
            }
          ]
        }
      ]
    },
    "tn:football::e-sweden::e-germany::": {
      "sbobetEventId": "tn:football::e-sweden::e-germany::",
      "sport": "football",
      "homeTeam": "e-Sweden (RIVAL)",
      "awayTeam": "e-Germany (DECIMATOR)",
      "startTime": null,
      "competition": null,
      "markets": [
        {
          "oddsId": "701273989",
          "marketType": "AH",
          "scope": "full",
          "line": 0.5,
          "runners": [
            {
              "selection": "HOME",
              "decimalOdds": 1.59
            },
            {
              "selection": "AWAY",
              "decimalOdds": 2.09
            }
          ]
        }
      ]
    },
    "tn:football::e-croatia::e-sweden::": {
      "sbobetEventId": "tn:football::e-croatia::e-sweden::",
      "sport": "football",
      "homeTeam": "e-Croatia (TROOPER)",
      "awayTeam": "e-Sweden (STORM)",
      "startTime": null,
      "competition": null,
      "markets": [
        {
          "oddsId": "701274846",
          "marketType": "AH",
          "scope": "full",
          "line": 0.5,
          "runners": [
            {
              "selection": "HOME",
              "decimalOdds": 1.59
            },
            {
              "selection": "AWAY",
              "decimalOdds": 2.09
            }
          ]
        }
      ]
    },
    "tn:football::e-netherlands::e-usa::": {
      "sbobetEventId": "tn:football::e-netherlands::e-usa::",
      "sport": "football",
      "homeTeam": "e-Netherlands (TEMPEST)",
      "awayTeam": "e-USA (JAEGER)",
      "startTime": null,
      "competition": null,
      "markets": [
        {
          "oddsId": "701275779",
          "marketType": "AH",
          "scope": "full",
          "line": -0.5,
          "runners": [
            {
              "selection": "HOME",
              "decimalOdds": 2.2
            },
            {
              "selection": "AWAY",
              "decimalOdds": 1.53
            }
          ]
        }
      ]
    },
    "tn:football::e-paris sg::e- bayern munchen::": {
      "sbobetEventId": "tn:football::e-paris sg::e- bayern munchen::",
      "sport": "football",
      "homeTeam": "e-Paris SG (ZEUS)",
      "awayTeam": "e-FC Bayern Munchen (THREAT)",
      "startTime": null,
      "competition": null,
      "markets": [
        {
          "oddsId": "701276633",
          "marketType": "AH",
          "scope": "full",
          "line": 0.5,
          "runners": [
            {
              "selection": "HOME",
              "decimalOdds": 1.59
            },
            {
              "selection": "AWAY",
              "decimalOdds": 2.09
            }
          ]
        }
      ]
    },
    "tn:football::e-spurs::e-newcastle utd::": {
      "sbobetEventId": "tn:football::e-spurs::e-newcastle utd::",
      "sport": "football",
      "homeTeam": "e-Spurs (RIVAL)",
      "awayTeam": "e-Newcastle UTD (ENT)",
      "startTime": null,
      "competition": null,
      "markets": [
        {
          "oddsId": "701281409",
          "marketType": "AH",
          "scope": "full",
          "line": 0.5,
          "runners": [
            {
              "selection": "HOME",
              "decimalOdds": 1.74
            },
            {
              "selection": "AWAY",
              "decimalOdds": 1.92
            }
          ]
        }
      ]
    },
    "tn:football::e-england::e-usa::": {
      "sbobetEventId": "tn:football::e-england::e-usa::",
      "sport": "football",
      "homeTeam": "e-England (TROOPER)",
      "awayTeam": "e-USA (ODYSSEY)",
      "startTime": null,
      "competition": null,
      "markets": [
        {
          "oddsId": "701299089",
          "marketType": "AH",
          "scope": "full",
          "line": 0.5,
          "runners": [
            {
              "selection": "HOME",
              "decimalOdds": 1.59
            },
            {
              "selection": "AWAY",
              "decimalOdds": 2.09
            }
          ]
        }
      ]
    },
    "tn:football::e-germany::e-england::": {
      "sbobetEventId": "tn:football::e-germany::e-england::",
      "sport": "football",
      "homeTeam": "e-Germany (INFERNO)",
      "awayTeam": "e-England (FORCE)",
      "startTime": null,
      "competition": null,
      "markets": [
        {
          "oddsId": "701307637",
          "marketType": "AH",
          "scope": "full",
          "line": -0.5,
          "runners": [
            {
              "selection": "HOME",
              "decimalOdds": 1.65
            },
            {
              "selection": "AWAY",
              "decimalOdds": 2.02
            }
          ]
        }
      ]
    },
    "tn:football::e-manchester city::e-real madrid::": {
      "sbobetEventId": "tn:football::e-manchester city::e-real madrid::",
      "sport": "football",
      "homeTeam": "e-Manchester City (GRIMACE)",
      "awayTeam": "e-Real Madrid (RESISTANCE)",
      "startTime": null,
      "competition": null,
      "markets": [
        {
          "oddsId": "701309004",
          "marketType": "AH",
          "scope": "full",
          "line": -0.5,
          "runners": [
            {
              "selection": "HOME",
              "decimalOdds": 1.89
            },
            {
              "selection": "AWAY",
              "decimalOdds": 1.77
            }
          ]
        }
      ]
    },
    "tn:football::e-aston villa::e-arsenal::": {
      "sbobetEventId": "tn:football::e-aston villa::e-arsenal::",
      "sport": "football",
      "homeTeam": "e-Aston Villa (DECIMATOR)",
      "awayTeam": "e-Arsenal (CROWN)",
      "startTime": null,
      "competition": null,
      "markets": [
        {
          "oddsId": "701310033",
          "marketType": "AH",
          "scope": "full",
          "line": -0.5,
          "runners": [
            {
              "selection": "HOME",
              "decimalOdds": 2.14
            },
            {
              "selection": "AWAY",
              "decimalOdds": 1.56
            }
          ]
        }
      ]
    },
    "tn:football::e-germany::e-sweden::": {
      "sbobetEventId": "tn:football::e-germany::e-sweden::",
      "sport": "football",
      "homeTeam": "e-Germany (STORM)",
      "awayTeam": "e-Sweden (MARS)",
      "startTime": null,
      "competition": null,
      "markets": [
        {
          "oddsId": "701311239",
          "marketType": "AH",
          "scope": "full",
          "line": -0.5,
          "runners": [
            {
              "selection": "HOME",
              "decimalOdds": 2.09
            },
            {
              "selection": "AWAY",
              "decimalOdds": 1.59
            }
          ]
        }
      ]
    },
    "tn:football::e-usa::e-germany::": {
      "sbobetEventId": "tn:football::e-usa::e-germany::",
      "sport": "football",
      "homeTeam": "e-USA (JAEGER)",
      "awayTeam": "e-Germany (INFERNO)",
      "startTime": null,
      "competition": null,
      "markets": [
        {
          "oddsId": "701312093",
          "marketType": "AH",
          "scope": "full",
          "line": 1.5,
          "runners": [
            {
              "selection": "HOME",
              "decimalOdds": 1.47
            },
            {
              "selection": "AWAY",
              "decimalOdds": 2.31
            }
          ]
        }
      ]
    },
    "tn:football::e- bayern munchen::e-manchester city::": {
      "sbobetEventId": "tn:football::e- bayern munchen::e-manchester city::",
      "sport": "football",
      "homeTeam": "e-FC Bayern Munchen (THREAT)",
      "awayTeam": "e-Manchester City (GRIMACE)",
      "startTime": null,
      "competition": null,
      "markets": [
        {
          "oddsId": "701313080",
          "marketType": "AH",
          "scope": "full",
          "line": -0.5,
          "runners": [
            {
              "selection": "HOME",
              "decimalOdds": 2.25
            },
            {
              "selection": "AWAY",
              "decimalOdds": 1.5
            }
          ]
        }
      ]
    },
    "tn:football::e-newcastle utd::e-aston villa::": {
      "sbobetEventId": "tn:football::e-newcastle utd::e-aston villa::",
      "sport": "football",
      "homeTeam": "e-Newcastle UTD (ENT)",
      "awayTeam": "e-Aston Villa (DECIMATOR)",
      "startTime": null,
      "competition": null,
      "markets": [
        {
          "oddsId": "701314013",
          "marketType": "AH",
          "scope": "full",
          "line": -0.5,
          "runners": [
            {
              "selection": "HOME",
              "decimalOdds": 2.09
            },
            {
              "selection": "AWAY",
              "decimalOdds": 1.59
            }
          ]
        }
      ]
    },
    "tn:football::e-usa::e-england::": {
      "sbobetEventId": "tn:football::e-usa::e-england::",
      "sport": "football",
      "homeTeam": "e-USA (ODYSSEY)",
      "awayTeam": "e-England (STORM)",
      "startTime": null,
      "competition": null,
      "markets": [
        {
          "oddsId": "701315054",
          "marketType": "AH",
          "scope": "full",
          "line": 0.5,
          "runners": [
            {
              "selection": "HOME",
              "decimalOdds": 1.53
            },
            {
              "selection": "AWAY",
              "decimalOdds": 2.2
            }
          ]
        }
      ]
    },
    "tn:football::e-england::e-netherlands::": {
      "sbobetEventId": "tn:football::e-england::e-netherlands::",
      "sport": "football",
      "homeTeam": "e-England (FORCE)",
      "awayTeam": "e-Netherlands (TEMPEST)",
      "startTime": null,
      "competition": null,
      "markets": [
        {
          "oddsId": "701315777",
          "marketType": "AH",
          "scope": "full",
          "line": -0.5,
          "runners": [
            {
              "selection": "HOME",
              "decimalOdds": 2.06
            },
            {
              "selection": "AWAY",
              "decimalOdds": 1.62
            }
          ]
        }
      ]
    },
    "tn:tennis::nasridinov amirkhamza::joshua charlton::2026-07-02T03:05:00.000Z": {
      "sbobetEventId": "tn:tennis::nasridinov amirkhamza::joshua charlton::2026-07-02T03:05:00.000Z",
      "sport": "tennis",
      "homeTeam": "Nasridinov Amirkhamza",
      "awayTeam": "Joshua Charlton",
      "startTime": "2026-07-02T03:05:00.000Z",
      "competition": null,
      "markets": [
        {
          "oddsId": "701963747",
          "marketType": "AH",
          "scope": "full",
          "line": 1.5,
          "runners": [
            {
              "selection": "HOME",
              "decimalOdds": 1.48
            },
            {
              "selection": "AWAY",
              "decimalOdds": 2.4
            }
          ]
        },
        {
          "oddsId": "701963750",
          "marketType": "AH",
          "scope": "full",
          "line": -1.5,
          "runners": [
            {
              "selection": "HOME",
              "decimalOdds": 3
            },
            {
              "selection": "AWAY",
              "decimalOdds": 1.31
            }
          ]
        }
      ]
    },
    "tn:tennis::yuto oki::kokoro isomura::2026-07-02T03:00:00.000Z": {
      "sbobetEventId": "tn:tennis::yuto oki::kokoro isomura::2026-07-02T03:00:00.000Z",
      "sport": "tennis",
      "homeTeam": "Yuto Oki",
      "awayTeam": "Kokoro Isomura",
      "startTime": "2026-07-02T03:00:00.000Z",
      "competition": null,
      "markets": [
        {
          "oddsId": "702052180",
          "marketType": "AH",
          "scope": "full",
          "line": 1.5,
          "runners": [
            {
              "selection": "HOME",
              "decimalOdds": 1.46
            },
            {
              "selection": "AWAY",
              "decimalOdds": 2.47
            }
          ]
        },
        {
          "oddsId": "702052182",
          "marketType": "AH",
          "scope": "full",
          "line": -1.5,
          "runners": [
            {
              "selection": "HOME",
              "decimalOdds": 3.04
            },
            {
              "selection": "AWAY",
              "decimalOdds": 1.3
            }
          ]
        }
      ]
    },
    "tn:tennis::reiya komagata::koki matsuda::2026-07-02T03:00:00.000Z": {
      "sbobetEventId": "tn:tennis::reiya komagata::koki matsuda::2026-07-02T03:00:00.000Z",
      "sport": "tennis",
      "homeTeam": "Reiya Komagata",
      "awayTeam": "Koki Matsuda",
      "startTime": "2026-07-02T03:00:00.000Z",
      "competition": null,
      "markets": [
        {
          "oddsId": "702052138",
          "marketType": "AH",
          "scope": "full",
          "line": 1.5,
          "runners": [
            {
              "selection": "HOME",
              "decimalOdds": 2.92
            },
            {
              "selection": "AWAY",
              "decimalOdds": 1.33
            }
          ]
        }
      ]
    },
    "tn:tennis::taisei ichikawa::kasidit samrej::2026-07-02T03:00:00.000Z": {
      "sbobetEventId": "tn:tennis::taisei ichikawa::kasidit samrej::2026-07-02T03:00:00.000Z",
      "sport": "tennis",
      "homeTeam": "Taisei Ichikawa",
      "awayTeam": "Kasidit Samrej",
      "startTime": "2026-07-02T03:00:00.000Z",
      "competition": null,
      "markets": [
        {
          "oddsId": "702052187",
          "marketType": "AH",
          "scope": "full",
          "line": 1.5,
          "runners": [
            {
              "selection": "HOME",
              "decimalOdds": 1.82
            },
            {
              "selection": "AWAY",
              "decimalOdds": 1.88
            }
          ]
        }
      ]
    },
    "tn:tennis::yuhan wang::jiaqi wang::2026-07-02T03:30:00.000Z": {
      "sbobetEventId": "tn:tennis::yuhan wang::jiaqi wang::2026-07-02T03:30:00.000Z",
      "sport": "tennis",
      "homeTeam": "Yuhan Wang",
      "awayTeam": "Jiaqi Wang",
      "startTime": "2026-07-02T03:30:00.000Z",
      "competition": null,
      "markets": [
        {
          "oddsId": "701994794",
          "marketType": "AH",
          "scope": "full",
          "line": 1.5,
          "runners": [
            {
              "selection": "HOME",
              "decimalOdds": 1.72
            },
            {
              "selection": "AWAY",
              "decimalOdds": 1.97
            }
          ]
        }
      ]
    },
    "tn:tennis::maria kalyakina::meiling wang::2026-07-02T03:30:00.000Z": {
      "sbobetEventId": "tn:tennis::maria kalyakina::meiling wang::2026-07-02T03:30:00.000Z",
      "sport": "tennis",
      "homeTeam": "Maria Kalyakina",
      "awayTeam": "Meiling Wang",
      "startTime": "2026-07-02T03:30:00.000Z",
      "competition": null,
      "markets": [
        {
          "oddsId": "701994862",
          "marketType": "AH",
          "scope": "full",
          "line": 1.5,
          "runners": [
            {
              "selection": "HOME",
              "decimalOdds": 1.45
            },
            {
              "selection": "AWAY",
              "decimalOdds": 2.47
            }
          ]
        },
        {
          "oddsId": "701994864",
          "marketType": "AH",
          "scope": "full",
          "line": -1.5,
          "runners": [
            {
              "selection": "HOME",
              "decimalOdds": 3.12
            },
            {
              "selection": "AWAY",
              "decimalOdds": 1.28
            }
          ]
        }
      ]
    }
  },
  "summary": {
    "urls": [
      "https://www.sbobet.com/en/euro/football",
      "https://www.sbobet.com/en/euro/tennis",
      "https://www.sbobet.com/en/euro/basketball",
      "https://www.sbobet.com/en/euro/baseball"
    ],
    "rawRows": 112,
    "events": 38,
    "markets": 41,
    "ahMarkets": 25,
    "ml1x2Markets": 16,
    "durationMs": 6654
  }
}